ProtCHOIR/AnalyseOligomer.py
ProtCHOIR/AnalyseProtomer.py
ProtCHOIR/Initialise.py
ProtCHOIR/MakeOligomer.py
ProtCHOIR/Toolbox.py
ProtCHOIR/UpdateDatabases.py
ProtCHOIR/__init__.py
ProtCHOIR/__main__.py
ProtCHOIR/Contents/ProtCHOIR (2).svg
ProtCHOIR/Contents/ProtCHOIR.svg
ProtCHOIR/Contents/ProtCHOIRReport.svg
ProtCHOIR/Contents/ProtCHOIRScheme.svg
ProtCHOIR/Contents/report_template.html
ProtCHOIR-1.2.25.dist-info/LICENSE.txt
ProtCHOIR-1.2.25.dist-info/METADATA
ProtCHOIR-1.2.25.dist-info/WHEEL
ProtCHOIR-1.2.25.dist-info/entry_points.txt
ProtCHOIR-1.2.25.dist-info/top_level.txt
ProtCHOIR-1.2.25.dist-info/RECORD
