Metadata-Version: 2.1
Name: ProtCHOIR
Version: 1.2.25
Summary: A Modeller-based pipeline to generate homo-oligomers.
Home-page: https://github.com/monteirotorres/ProtCHOIR
Author: Pedro Torres, Tom Blundell
Author-email: monteirotorres@biof.ufrj.br
License: CC-BY-4.0
Keywords: PDB,structure,protein,oligomerization,oligomers,multimer
License-File: LICENSE.txt
Requires-Dist: pandas
Requires-Dist: progressbar2
Requires-Dist: biopython
Requires-Dist: parasail
Requires-Dist: matplotlib
Requires-Dist: numpy
Requires-Dist: jinja2
Requires-Dist: networkx
